autogen_voting/__init__.py
autogen_voting/config.py
autogen_voting/py.typed
autogen_voting/voting_group_chat.py
autogen_voting_extension-0.1.0.dist-info/licenses/LICENSE
autogen_voting_extension-0.1.0.dist-info/METADATA
autogen_voting_extension-0.1.0.dist-info/WHEEL
autogen_voting_extension-0.1.0.dist-info/top_level.txt
autogen_voting_extension-0.1.0.dist-info/RECORD
